pbstool/__init__.py
pbstool/__main__.py
pbstool/generate.py
pbstool-2.2.dist-info/LICENSE
pbstool-2.2.dist-info/METADATA
pbstool-2.2.dist-info/WHEEL
pbstool-2.2.dist-info/entry_points.txt
pbstool-2.2.dist-info/top_level.txt
pbstool-2.2.dist-info/RECORD
