Metadata-Version: 2.1
Name: pbstool
Version: 2.2
Summary: A simple-to-use program for quickly batch creating job tasks based on the PBS job scheduling system (including OpenPBS, PBS Pro, and TORQUE) based on a command list.
Home-page: https://github.com/interestingcn/pbstool
Author: ['wangzt']
Author-email: interestingcn01@gmail.com
Classifier: Development Status :: 5 - Production/Stable
Classifier: License :: OSI Approved :: Apache Software License
Classifier: Operating System :: OS Independent
Classifier: Programming Language :: Python :: 3.5
Classifier: Programming Language :: Python :: 3.6
Classifier: Programming Language :: Python :: 3.7
Classifier: Programming Language :: Python :: 3.8
Classifier: Programming Language :: Python :: 3.9
Classifier: Programming Language :: Python :: 3.10
Classifier: Programming Language :: Python :: 3.11
Requires-Python: >=3.5
License-File: LICENSE
Requires-Dist: tqdm
